dsgepy/__init__.py
dsgepy/data_api.py
dsgepy/lineardsge.py
dsgepy/pycsminwel.py
dsgepy/kalman/__init__.py
dsgepy/kalman/kalman.py
dsgepy/kalman/utils.py
dsgepy-1.1.dist-info/licenses/LICENSE
dsgepy-1.1.dist-info/METADATA
dsgepy-1.1.dist-info/WHEEL
dsgepy-1.1.dist-info/top_level.txt
dsgepy-1.1.dist-info/RECORD
