Metadata-Version: 2.4
Name: dsgepy
Version: 1.1
Summary: Solve and estimate linearized DSGE models
Author: Gustavo Amarante
Author-email: gusamarante@gmail.com
Keywords: dsge,macroeconomics
License-File: LICENSE
Requires-Dist: matplotlib
Requires-Dist: numpy
Requires-Dist: pandas
Requires-Dist: scipy
Requires-Dist: sympy
Requires-Dist: tqdm
Dynamic: author
Dynamic: author-email
Dynamic: description
Dynamic: description-content-type
Dynamic: keywords
Dynamic: license-file
Dynamic: requires-dist
Dynamic: summary
